{"fn": [{"id": 512177, "mc": 139, "oc": 6}, {"id": 659678, "mc": 28, "oc": 12}, {"id": 675001, "mc": 21, "oc": 1}], "fngentertainment": [{"id": 517133, "mc": 79, "oc": 9}, {"id": 570830, "mc": 8, "oc": 3}], "fnflyxbot": [{"id": 522696, "mc": 144, "oc": 19}], "fnntasy": [{"id": 526110, "mc": 84, "oc": 17}], "fng1000": [{"id": 533855, "mc": 212, "oc": 3}], "fnhusa57": [{"id": 538621, "mc": 416, "oc": 28}], "fnfnation": [{"id": 538908, "mc": 62, "oc": 7}], "fnttoken4098": [{"id": 550945, "mc": 1, "oc": 0}], "fnignale": [{"id": 553503, "mc": 7, "oc": 4}], "fncyt": [{"id": 555075, "mc": 3230, "oc": 169}], "fnonn": [{"id": 556152, "mc": 2688, "oc": 517}], "fns233": [{"id": 559617, "mc": 133, "oc": 15}], "fnaf10124": [{"id": 568037, "mc": 23, "oc": 8}], "fncgpt": [{"id": 575436, "mc": 142, "oc": 44}], "fnscence": [{"id": 585560, "mc": 3156, "oc": 353}], "fnzyn": [{"id": 588705, "mc": 1084, "oc": 63}], "fnvertical": [{"id": 598205, "mc": 2, "oc": 0}], "fncsagent007": [{"id": 618682, "mc": 10, "oc": 4}], "fnzgl2070": [{"id": 618767, "mc": 5, "oc": 0}], "fnjpnew": [{"id": 633415, "mc": 52, "oc": 4}], "fnbrwatch": [{"id": 636121, "mc": 19, "oc": 3}], "fnvisual": [{"id": 640742, "mc": 15236, "oc": 2017}], "fnafdude": [{"id": 646922, "mc": 9, "oc": 3}], "fnf": [{"id": 666009, "mc": 5, "oc": 0}], "fna5tartrooper": [{"id": 667913, "mc": 57, "oc": 6}], "fnightshade": [{"id": 670266, "mc": 11, "oc": 3}], "fndy": [{"id": 672161, "mc": 526, "oc": 24}], "fnlev": [{"id": 686637, "mc": 19, "oc": 5}], "fnnick": [{"id": 699341, "mc": 10, "oc": 2}], "fnok": [{"id": 702343, "mc": 159, "oc": 33}], "fntwofficial": [{"id": 708427, "mc": 312, "oc": 16}], "fnacportugal": [{"id": 711877, "mc": 956, "oc": 21}], "fnn": [{"id": 726334, "mc": 2437, "oc": 300}], "fndmn4cryt": [{"id": 728306, "mc": 3, "oc": 1}], "fnnybnny": [{"id": 729554, "mc": 14, "oc": 3}], "fnoji": [{"id": 730900, "mc": 307, "oc": 86}], "fncssync": [{"id": 732800, "mc": 124, "oc": 31}], "fnnf": [{"id": 735388, "mc": 844, "oc": 69}], "fnblender0912": [{"id": 735827, "mc": 10, "oc": 1}], "fndlymr": [{"id": 738384, "mc": 46, "oc": 9}], "fnaflover8783": [{"id": 746990, "mc": 22, "oc": 5}], "fnafnews19877857": [{"id": 749231, "mc": 6, "oc": 4}], "fnwaterjpnew": [{"id": 749572, "mc": 2, "oc": 0}]}