{"xzow8869": [{"id": 510136, "mc": 49, "oc": 6}], "xzac": [{"id": 512548, "mc": 1464, "oc": 129}], "xzybu": [{"id": 534649, "mc": 9502, "oc": 2706}], "xztz": [{"id": 548279, "mc": 7, "oc": 4}], "xzntrc": [{"id": 560236, "mc": 981, "oc": 171}], "xzerkzi": [{"id": 562330, "mc": 21, "oc": 3}], "xzc9y1": [{"id": 562763, "mc": 103, "oc": 1}], "xzeroair": [{"id": 564917, "mc": 279, "oc": 61}], "xzvzxvzxv1": [{"id": 565979, "mc": 303, "oc": 17}], "xzureth": [{"id": 569967, "mc": 111, "oc": 21}], "xzc": [{"id": 577550, "mc": 10, "oc": 6}], "xzz": [{"id": 583357, "mc": 15, "oc": 7}], "xzhm": [{"id": 588324, "mc": 97, "oc": 12}], "xzy231": [{"id": 595707, "mc": 166, "oc": 38}], "xzxlordxzx": [{"id": 602861, "mc": 554, "oc": 40}], "xzbid": [{"id": 604778, "mc": 769, "oc": 111}], "xz1fy": [{"id": 614965, "mc": 32, "oc": 6}], "xzayfinesse": [{"id": 617655, "mc": 65, "oc": 9}], "xziron": [{"id": 621018, "mc": 238, "oc": 44}], "xzeroinovuszz": [{"id": 624985, "mc": 35, "oc": 6}], "xzavain": [{"id": 629419, "mc": 23, "oc": 7}], "xzay": [{"id": 633585, "mc": 316, "oc": 41}], "xzey": [{"id": 640003, "mc": 1095, "oc": 98}], "xzensdev2110": [{"id": 660624, "mc": 130, "oc": 5}], "xzxsnowmanxzx": [{"id": 666226, "mc": 23, "oc": 8}], "xzcvwz": [{"id": 672433, "mc": 1125, "oc": 65}], "xzoaura": [{"id": 674538, "mc": 906, "oc": 75}], "xzybi2287": [{"id": 678806, "mc": 1, "oc": 0}], "xzaguer": [{"id": 682107, "mc": 553, "oc": 151}], "xzippyzachx": [{"id": 696232, "mc": 1044, "oc": 152}], "xzandro": [{"id": 720746, "mc": 10312, "oc": 1607}], "xzon7": [{"id": 721815, "mc": 28, "oc": 0}], "xzyangx": [{"id": 745065, "mc": 12, "oc": 3}]}