{"agency": [{"id": 500083, "mc": 61, "oc": 9}, {"id": 501891, "mc": 33, "oc": 8}, {"id": 502347, "mc": 66, "oc": 6}, {"id": 503811, "mc": 313, "oc": 6}, {"id": 505049, "mc": 411, "oc": 96}, {"id": 512567, "mc": 539, "oc": 188}, {"id": 520057, "mc": 597, "oc": 42}, {"id": 522516, "mc": 424, "oc": 10}, {"id": 533070, "mc": 2708, "oc": 35}, {"id": 533954, "mc": 115, "oc": 17}, {"id": 540450, "mc": 266, "oc": 42}, {"id": 544862, "mc": 40, "oc": 8}, {"id": 555852, "mc": 2, "oc": 0}, {"id": 556204, "mc": 85, "oc": 3}, {"id": 556648, "mc": 168, "oc": 11}, {"id": 560766, "mc": 875, "oc": 46}, {"id": 563628, "mc": 442, "oc": 101}, {"id": 564133, "mc": 794, "oc": 228}, {"id": 567327, "mc": 325, "oc": 83}, {"id": 568067, "mc": 13, "oc": 5}, {"id": 575042, "mc": 24, "oc": 4}, {"id": 575822, "mc": 274, "oc": 9}, {"id": 577007, "mc": 804, "oc": 114}, {"id": 581441, "mc": 314, "oc": 27}, {"id": 588291, "mc": 688, "oc": 201}, {"id": 590695, "mc": 8, "oc": 1}, {"id": 592174, "mc": 137, "oc": 2}, {"id": 597393, "mc": 63, "oc": 18}, {"id": 597492, "mc": 15, "oc": 7}, {"id": 598387, "mc": 75, "oc": 12}, {"id": 600317, "mc": 35, "oc": 8}, {"id": 614573, "mc": 1, "oc": 1}, {"id": 615950, "mc": 63, "oc": 8}, {"id": 618394, "mc": 169, "oc": 20}, {"id": 619467, "mc": 125, "oc": 44}, {"id": 621677, "mc": 30, "oc": 11}, {"id": 622081, "mc": 106, "oc": 24}, {"id": 623434, "mc": 139, "oc": 4}, {"id": 626955, "mc": 10, "oc": 0}, {"id": 634981, "mc": 2354, "oc": 76}, {"id": 638450, "mc": 141, "oc": 12}, {"id": 641548, "mc": 212, "oc": 25}, {"id": 643545, "mc": 1, "oc": 0}, {"id": 645618, "mc": 57, "oc": 5}, {"id": 648297, "mc": 8, "oc": 4}, {"id": 653174, "mc": 507, "oc": 84}, {"id": 655825, "mc": 14, "oc": 4}, {"id": 660209, "mc": 5, "oc": 2}, {"id": 662627, "mc": 5, "oc": 0}, {"id": 663371, "mc": 258, "oc": 34}, {"id": 666476, "mc": 67, "oc": 18}, {"id": 671476, "mc": 1033, "oc": 69}, {"id": 673070, "mc": 57, "oc": 3}, {"id": 677852, "mc": 138, "oc": 18}, {"id": 681051, "mc": 49, "oc": 27}, {"id": 683887, "mc": 90, "oc": 8}, {"id": 684283, "mc": 126, "oc": 2}, {"id": 686827, "mc": 75, "oc": 10}, {"id": 692115, "mc": 3078, "oc": 61}, {"id": 697369, "mc": 2445, "oc": 214}, {"id": 714737, "mc": 75, "oc": 4}, {"id": 717299, "mc": 77, "oc": 17}, {"id": 718660, "mc": 26, "oc": 14}, {"id": 721441, "mc": 17, "oc": 7}, {"id": 725120, "mc": 81, "oc": 14}, {"id": 725471, "mc": 169, "oc": 9}, {"id": 728439, "mc": 21, "oc": 2}, {"id": 730339, "mc": 80, "oc": 9}, {"id": 731489, "mc": 30, "oc": 8}, {"id": 733565, "mc": 65, "oc": 23}, {"id": 736768, "mc": 49, "oc": 28}, {"id": 739838, "mc": 18, "oc": 4}, {"id": 741872, "mc": 16, "oc": 10}, {"id": 747854, "mc": 138, "oc": 4}, {"id": 748767, "mc": 1534, "oc": 69}], "againstpolarization": [{"id": 500795, "mc": 1, "oc": 0}], "against": [{"id": 501891, "mc": 33, "oc": 8}, {"id": 516399, "mc": 5, "oc": 0}, {"id": 520767, "mc": 99, "oc": 7}, {"id": 522848, "mc": 23, "oc": 9}, {"id": 526650, "mc": 2, "oc": 0}, {"id": 530480, "mc": 3, "oc": 0}, {"id": 546702, "mc": 282, "oc": 46}, {"id": 553849, "mc": 3532, "oc": 210}, {"id": 568080, "mc": 34, "oc": 13}, {"id": 570784, "mc": 98, "oc": 12}, {"id": 572022, "mc": 140, "oc": 19}, {"id": 577757, "mc": 26, "oc": 1}, {"id": 579015, "mc": 107, "oc": 22}, {"id": 588332, "mc": 6947, "oc": 882}, {"id": 605259, "mc": 115, "oc": 32}, {"id": 613156, "mc": 3, "oc": 0}, {"id": 613709, "mc": 246, "oc": 28}, {"id": 630989, "mc": 392, "oc": 79}, {"id": 642400, "mc": 238, "oc": 70}, {"id": 648927, "mc": 22, "oc": 1}, {"id": 650627, "mc": 82, "oc": 4}, {"id": 652026, "mc": 32, "oc": 12}, {"id": 657185, "mc": 3, "oc": 2}, {"id": 661321, "mc": 240, "oc": 8}, {"id": 685614, "mc": 22, "oc": 4}, {"id": 686912, "mc": 88, "oc": 8}, {"id": 689608, "mc": 240, "oc": 63}, {"id": 691211, "mc": 105, "oc": 10}, {"id": 702970, "mc": 295, "oc": 5}, {"id": 703206, "mc": 3, "oc": 2}, {"id": 725986, "mc": 237, "oc": 92}, {"id": 729116, "mc": 12, "oc": 5}, {"id": 732257, "mc": 233, "oc": 40}, {"id": 733305, "mc": 10, "oc": 6}, {"id": 735039, "mc": 612, "oc": 44}], "agent": [{"id": 502366, "mc": 7, "oc": 4}, {"id": 502936, "mc": 481, "oc": 69}, {"id": 503228, "mc": 355, "oc": 36}, {"id": 503811, "mc": 313, "oc": 6}, {"id": 504650, "mc": 58, "oc": 26}, {"id": 509682, "mc": 579, "oc": 114}, {"id": 511858, "mc": 4, "oc": 1}, {"id": 524025, "mc": 187, "oc": 3}, {"id": 525023, "mc": 24, "oc": 6}, {"id": 527002, "mc": 653, "oc": 59}, {"id": 543096, "mc": 652, "oc": 85}, {"id": 546372, "mc": 1002, "oc": 184}, {"id": 546773, "mc": 3187, "oc": 361}, {"id": 549996, "mc": 96, "oc": 20}, {"id": 553415, "mc": 3643, "oc": 162}, {"id": 562925, "mc": 39, "oc": 7}, {"id": 567302, "mc": 35, "oc": 7}, {"id": 572853, "mc": 42, "oc": 1}, {"id": 573649, "mc": 13, "oc": 2}, {"id": 577182, "mc": 301, "oc": 38}, {"id": 585295, "mc": 29, "oc": 7}, {"id": 585371, "mc": 2058, "oc": 210}, {"id": 589556, "mc": 201, "oc": 33}, {"id": 602091, "mc": 165, "oc": 11}, {"id": 604170, "mc": 401, "oc": 75}, {"id": 604605, "mc": 2, "oc": 0}, {"id": 606991, "mc": 198, "oc": 12}, {"id": 612198, "mc": 199, "oc": 24}, {"id": 617608, "mc": 8202, "oc": 170}, {"id": 620728, "mc": 41, "oc": 5}, {"id": 625251, "mc": 55, "oc": 8}, {"id": 626672, "mc": 427, "oc": 62}, {"id": 631626, "mc": 54, "oc": 9}, {"id": 632984, "mc": 26, "oc": 7}, {"id": 633153, "mc": 105, "oc": 33}, {"id": 634438, "mc": 2337, "oc": 118}, {"id": 644467, "mc": 18, "oc": 7}, {"id": 647256, "mc": 161, "oc": 27}, {"id": 649032, "mc": 31, "oc": 3}, {"id": 649921, "mc": 79, "oc": 13}, {"id": 650293, "mc": 45, "oc": 8}, {"id": 654176, "mc": 5, "oc": 0}, {"id": 655015, "mc": 11, "oc": 1}, {"id": 669276, "mc": 502, "oc": 57}, {"id": 674036, "mc": 42, "oc": 15}, {"id": 680116, "mc": 156, "oc": 42}, {"id": 681588, "mc": 22, "oc": 3}, {"id": 683818, "mc": 614, "oc": 54}, {"id": 684108, "mc": 129, "oc": 38}, {"id": 694625, "mc": 174, "oc": 49}, {"id": 703878, "mc": 58, "oc": 8}, {"id": 706824, "mc": 42, "oc": 10}, {"id": 709354, "mc": 73, "oc": 10}, {"id": 717405, "mc": 1, "oc": 0}, {"id": 722946, "mc": 8, "oc": 2}, {"id": 737881, "mc": 1966, "oc": 326}, {"id": 738679, "mc": 92, "oc": 2}, {"id": 744550, "mc": 4, "oc": 2}, {"id": 744687, "mc": 95, "oc": 22}, {"id": 746777, "mc": 8, "oc": 0}], "ag": [{"id": 502637, "mc": 77, "oc": 14}, {"id": 524271, "mc": 5426, "oc": 715}, {"id": 557978, "mc": 1459, "oc": 254}, {"id": 567971, "mc": 428, "oc": 14}, {"id": 618694, "mc": 17, "oc": 2}, {"id": 628024, "mc": 16, "oc": 10}, {"id": 638594, "mc": 5, "oc": 3}, {"id": 639675, "mc": 15, "oc": 8}, {"id": 641415, "mc": 115, "oc": 6}, {"id": 651896, "mc": 812, "oc": 101}, {"id": 670764, "mc": 14, "oc": 9}, {"id": 674383, "mc": 4279, "oc": 828}, {"id": 680040, "mc": 48, "oc": 12}, {"id": 711620, "mc": 954, "oc": 14}, {"id": 719421, "mc": 129, "oc": 23}, {"id": 720397, "mc": 160, "oc": 16}], "agere": [{"id": 503248, "mc": 2, "oc": 0}, {"id": 664740, "mc": 218, "oc": 54}], "age": [{"id": 503563, "mc": 42, "oc": 4}, {"id": 505825, "mc": 94, "oc": 19}, {"id": 506245, "mc": 10, "oc": 5}, {"id": 509065, "mc": 549, "oc": 107}, {"id": 510446, "mc": 188, "oc": 30}, {"id": 514601, "mc": 9, "oc": 2}, {"id": 514969, "mc": 211, "oc": 10}, {"id": 518047, "mc": 25, "oc": 3}, {"id": 520002, "mc": 732, "oc": 83}, {"id": 520734, "mc": 6, "oc": 1}, {"id": 522159, "mc": 34, "oc": 6}, {"id": 523218, "mc": 6693, "oc": 108}, {"id": 527598, "mc": 5200, "oc": 265}, {"id": 528479, "mc": 75, "oc": 9}, {"id": 529780, "mc": 225, "oc": 30}, {"id": 535709, "mc": 818, "oc": 48}, {"id": 536198, "mc": 940, "oc": 212}, {"id": 536750, "mc": 450, "oc": 20}, {"id": 536800, "mc": 35, "oc": 8}, {"id": 537250, "mc": 156, "oc": 11}, {"id": 540041, "mc": 153, "oc": 33}, {"id": 541797, "mc": 6, "oc": 2}, {"id": 542272, "mc": 1721, "oc": 569}, {"id": 545174, "mc": 12, "oc": 3}, {"id": 549691, "mc": 7, "oc": 1}, {"id": 550772, "mc": 35, "oc": 8}, {"id": 551367, "mc": 2, "oc": 0}, {"id": 552046, "mc": 65, "oc": 5}, {"id": 553382, "mc": 25, "oc": 12}, {"id": 554386, "mc": 2302, "oc": 370}, {"id": 555060, "mc": 26, "oc": 3}, {"id": 556028, "mc": 45, "oc": 20}, {"id": 556058, "mc": 62, "oc": 8}, {"id": 559105, "mc": 25, "oc": 7}, {"id": 559440, "mc": 23, "oc": 3}, {"id": 560480, "mc": 47, "oc": 7}, {"id": 561295, "mc": 189, "oc": 45}, {"id": 562641, "mc": 70, "oc": 4}, {"id": 568429, "mc": 2, "oc": 0}, {"id": 568575, "mc": 169, "oc": 35}, {"id": 571079, "mc": 80, "oc": 18}, {"id": 571204, "mc": 58, "oc": 8}, {"id": 571850, "mc": 795, "oc": 210}, {"id": 576664, "mc": 9, "oc": 2}, {"id": 577048, "mc": 57, "oc": 10}, {"id": 581340, "mc": 782, "oc": 72}, {"id": 582060, "mc": 6, "oc": 5}, {"id": 585348, "mc": 2, "oc": 0}, {"id": 586719, "mc": 5, "oc": 1}, {"id": 588756, "mc": 11214, "oc": 1045}, {"id": 589531, "mc": 15, "oc": 1}, {"id": 589570, "mc": 552, "oc": 23}, {"id": 595023, "mc": 6, "oc": 1}, {"id": 597382, "mc": 17, "oc": 3}, {"id": 599314, "mc": 1111, "oc": 218}, {"id": 602065, "mc": 24, "oc": 6}, {"id": 605107, "mc": 1531, "oc": 94}, {"id": 607074, "mc": 129, "oc": 9}, {"id": 608376, "mc": 93, "oc": 19}, {"id": 608713, "mc": 340, "oc": 65}, {"id": 609483, "mc": 72, "oc": 15}, {"id": 609577, "mc": 978, "oc": 63}, {"id": 610719, "mc": 1, "oc": 0}, {"id": 613486, "mc": 629, "oc": 88}, {"id": 614108, "mc": 318, "oc": 57}, {"id": 617142, "mc": 478, "oc": 52}, {"id": 617756, "mc": 208, "oc": 15}, {"id": 628991, "mc": 35, "oc": 4}, {"id": 629646, "mc": 44, "oc": 13}, {"id": 631495, "mc": 285, "oc": 26}, {"id": 631746, "mc": 1160, "oc": 265}, {"id": 636874, "mc": 11, "oc": 3}, {"id": 639261, "mc": 322, "oc": 99}, {"id": 639316, "mc": 277, "oc": 80}, {"id": 640671, "mc": 35, "oc": 9}, {"id": 643187, "mc": 1364, "oc": 165}, {"id": 651801, "mc": 28, "oc": 5}, {"id": 656305, "mc": 1, "oc": 0}, {"id": 658140, "mc": 140, "oc": 25}, {"id": 658553, "mc": 9, "oc": 4}, {"id": 658961, "mc": 4, "oc": 0}, {"id": 659883, "mc": 2869, "oc": 10}, {"id": 660252, "mc": 429, "oc": 92}, {"id": 663423, "mc": 226, "oc": 19}, {"id": 663606, "mc": 414, "oc": 16}, {"id": 665881, "mc": 554, "oc": 222}, {"id": 667049, "mc": 4920, "oc": 266}, {"id": 669039, "mc": 22, "oc": 6}, {"id": 671520, "mc": 69, "oc": 15}, {"id": 672580, "mc": 96, "oc": 26}, {"id": 674599, "mc": 244, "oc": 8}, {"id": 676196, "mc": 242, "oc": 56}, {"id": 677033, "mc": 6, "oc": 1}, {"id": 677397, "mc": 8, "oc": 1}, {"id": 679486, "mc": 46, "oc": 5}, {"id": 680391, "mc": 174, "oc": 17}, {"id": 681280, "mc": 219, "oc": 23}, {"id": 682820, "mc": 7, "oc": 1}, {"id": 684051, "mc": 18, "oc": 7}, {"id": 686277, "mc": 1, "oc": 0}, {"id": 686752, "mc": 63, "oc": 6}, {"id": 687163, "mc": 76, "oc": 10}, {"id": 687980, "mc": 2, "oc": 1}, {"id": 691369, "mc": 158, "oc": 31}, {"id": 691650, "mc": 9, "oc": 5}, {"id": 694249, "mc": 111, "oc": 14}, {"id": 696258, "mc": 169882, "oc": 7097}, {"id": 697603, "mc": 1302, "oc": 188}, {"id": 698448, "mc": 16, "oc": 4}, {"id": 702795, "mc": 3, "oc": 2}, {"id": 707784, "mc": 4668, "oc": 1074}, {"id": 710201, "mc": 313, "oc": 96}, {"id": 711073, "mc": 130, "oc": 14}, {"id": 715758, "mc": 1499, "oc": 348}, {"id": 716788, "mc": 469, "oc": 53}, {"id": 717002, "mc": 1, "oc": 0}, {"id": 719519, "mc": 19, "oc": 10}, {"id": 719630, "mc": 4938, "oc": 252}, {"id": 721282, "mc": 15, "oc": 6}, {"id": 726791, "mc": 85, "oc": 5}, {"id": 727907, "mc": 28, "oc": 3}, {"id": 728533, "mc": 29, "oc": 12}, {"id": 730363, "mc": 179, "oc": 34}, {"id": 731037, "mc": 176, "oc": 58}, {"id": 734704, "mc": 67, "oc": 18}, {"id": 739824, "mc": 356, "oc": 72}, {"id": 741064, "mc": 3170, "oc": 686}, {"id": 741184, "mc": 25, "oc": 3}, {"id": 743127, "mc": 345, "oc": 59}, {"id": 744352, "mc": 22, "oc": 6}, {"id": 746387, "mc": 1688, "oc": 288}], "aggy": [{"id": 503631, "mc": 371, "oc": 67}], "aggregator": [{"id": 503728, "mc": 6, "oc": 2}, {"id": 509459, "mc": 747, "oc": 31}, {"id": 510890, "mc": 92, "oc": 11}], "agito": [{"id": 504228, "mc": 118, "oc": 32}], "agile": [{"id": 504347, "mc": 422, "oc": 28}, {"id": 538835, "mc": 24, "oc": 0}, {"id": 553982, "mc": 108, "oc": 21}, {"id": 554980, "mc": 130, "oc": 1}, {"id": 607822, "mc": 10, "oc": 1}, {"id": 665361, "mc": 64, "oc": 6}, {"id": 667850, "mc": 197, "oc": 16}, {"id": 707059, "mc": 1898, "oc": 104}, {"id": 727088, "mc": 6, "oc": 3}], "agencysecret": [{"id": 506131, "mc": 32505, "oc": 801}], "agn": [{"id": 508950, "mc": 3, "oc": 2}, {"id": 681709, "mc": 343, "oc": 58}], "agroville": [{"id": 509123, "mc": 23, "oc": 5}], "agrox": [{"id": 509321, "mc": 36, "oc": 4}], "again": [{"id": 509925, "mc": 49, "oc": 12}, {"id": 511354, "mc": 45, "oc": 8}, {"id": 516394, "mc": 34, "oc": 7}, {"id": 517712, "mc": 96, "oc": 16}, {"id": 536880, "mc": 38, "oc": 13}, {"id": 538451, "mc": 43, "oc": 8}, {"id": 561430, "mc": 1681, "oc": 325}, {"id": 575165, "mc": 5, "oc": 3}, {"id": 586695, "mc": 372, "oc": 54}, {"id": 593821, "mc": 9, "oc": 4}, {"id": 614184, "mc": 3, "oc": 1}, {"id": 639357, "mc": 52, "oc": 18}, {"id": 643687, "mc": 47, "oc": 14}, {"id": 662659, "mc": 13, "oc": 6}, {"id": 681424, "mc": 16, "oc": 6}, {"id": 703042, "mc": 836, "oc": 131}, {"id": 704598, "mc": 15, "oc": 7}, {"id": 720470, "mc": 1555, "oc": 42}, {"id": 728573, "mc": 1959, "oc": 55}, {"id": 741974, "mc": 98, "oc": 24}, {"id": 747441, "mc": 47, "oc": 9}], "agentliamtv": [{"id": 510501, "mc": 55, "oc": 11}], "agma": [{"id": 511280, "mc": 77, "oc": 9}], "aggie": [{"id": 511359, "mc": 266, "oc": 32}, {"id": 525816, "mc": 98, "oc": 6}, {"id": 688374, "mc": 371, "oc": 17}, {"id": 692913, "mc": 288, "oc": 25}, {"id": 701040, "mc": 10, "oc": 1}, {"id": 702345, "mc": 57, "oc": 20}, {"id": 720009, "mc": 1687, "oc": 77}], "agora": [{"id": 511478, "mc": 3, "oc": 0}, {"id": 527766, "mc": 254, "oc": 22}, {"id": 590226, "mc": 257, "oc": 66}, {"id": 614472, "mc": 11, "oc": 2}, {"id": 654600, "mc": 349, "oc": 30}, {"id": 655115, "mc": 11093, "oc": 910}, {"id": 673151, "mc": 176, "oc": 66}, {"id": 685756, "mc": 12, "oc": 6}, {"id": 686096, "mc": 88, "oc": 5}, {"id": 704462, "mc": 10, "oc": 5}, {"id": 710639, "mc": 3693, "oc": 644}, {"id": 715807, "mc": 1712, "oc": 25}], "agaricu": [{"id": 512749, "mc": 1, "oc": 0}], "agentserve": [{"id": 514171, "mc": 7, "oc": 0}], "agon": [{"id": 514279, "mc": 384, "oc": 68}], "aggression": [{"id": 514370, "mc": 23, "oc": 4}, {"id": 728199, "mc": 45, "oc": 5}], "agrar": [{"id": 516580, "mc": 45, "oc": 6}], "agentcloud": [{"id": 516878, "mc": 265, "oc": 16}], "agentrus": [{"id": 517307, "mc": 2953, "oc": 629}], "aged": [{"id": 517523, "mc": 10, "oc": 2}, {"id": 644233, "mc": 13, "oc": 0}], "agar": [{"id": 521959, "mc": 22, "oc": 1}, {"id": 526508, "mc": 2012, "oc": 104}, {"id": 597337, "mc": 13, "oc": 1}, {"id": 621520, "mc": 2737, "oc": 26}, {"id": 653278, "mc": 5, "oc": 0}, {"id": 726236, "mc": 70, "oc": 3}], "aggressively": [{"id": 523543, "mc": 34, "oc": 7}], "agoraphobic": [{"id": 527065, "mc": 5, "oc": 1}], "agartha": [{"id": 528575, "mc": 379, "oc": 69}, {"id": 708646, "mc": 3, "oc": 2}], "agame": [{"id": 528894, "mc": 1633, "oc": 535}], "agc": [{"id": 529139, "mc": 44, "oc": 8}, {"id": 617938, "mc": 158, "oc": 15}, {"id": 700493, "mc": 350, "oc": 54}], "aggravated": [{"id": 529295, "mc": 9367, "oc": 244}], "agress0r": [{"id": 529931, "mc": 1664, "oc": 316}], "ags": [{"id": 530384, "mc": 589, "oc": 85}, {"id": 542051, "mc": 2, "oc": 1}, {"id": 689213, "mc": 130, "oc": 37}, {"id": 717587, "mc": 7, "oc": 2}], "agrospol": [{"id": 530648, "mc": 615, "oc": 51}], "agentz": [{"id": 534288, "mc": 124, "oc": 25}], "agr": [{"id": 534493, "mc": 2800, "oc": 552}], "aggressor": [{"id": 534601, "mc": 46, "oc": 9}], "agilitateur": [{"id": 535527, "mc": 50, "oc": 6}], "agentwabbit": [{"id": 536779, "mc": 49, "oc": 12}], "agonest": [{"id": 537069, "mc": 1, "oc": 0}], "aggieseek": [{"id": 539933, "mc": 606, "oc": 41}], "agenda": [{"id": 541362, "mc": 209, "oc": 33}, {"id": 548971, "mc": 5516, "oc": 1154}, {"id": 627824, "mc": 67, "oc": 16}, {"id": 643845, "mc": 43, "oc": 4}, {"id": 652474, "mc": 37, "oc": 5}, {"id": 696239, "mc": 878, "oc": 146}, {"id": 710945, "mc": 37, "oc": 8}], "aggro": [{"id": 544133, "mc": 71, "oc": 18}, {"id": 582558, "mc": 82, "oc": 19}, {"id": 609607, "mc": 106, "oc": 19}, {"id": 685780, "mc": 161, "oc": 29}, {"id": 699523, "mc": 57, "oc": 22}], "agia": [{"id": 544529, "mc": 4, "oc": 1}], "agogigi": [{"id": 545657, "mc": 259, "oc": 71}], "agama": [{"id": 545858, "mc": 6, "oc": 3}], "agpg": [{"id": 546545, "mc": 405, "oc": 61}], "agentic": [{"id": 548056, "mc": 8, "oc": 1}], "ageles": [{"id": 551002, "mc": 31, "oc": 8}], "agoraphobia": [{"id": 552158, "mc": 67, "oc": 11}, {"id": 701048, "mc": 510, "oc": 56}], "agsb": [{"id": 553124, "mc": 19, "oc": 4}], "agarclan": [{"id": 554602, "mc": 2, "oc": 1}], "agi": [{"id": 556128, "mc": 123, "oc": 3}, {"id": 632599, "mc": 22, "oc": 3}, {"id": 691360, "mc": 17, "oc": 5}, {"id": 704927, "mc": 203, "oc": 51}, {"id": 741510, "mc": 188, "oc": 9}], "agkdog": [{"id": 556896, "mc": 6, "oc": 3}], "agila": [{"id": 557531, "mc": 724, "oc": 145}], "agl": [{"id": 557599, "mc": 19, "oc": 4}, {"id": 653621, "mc": 5, "oc": 1}], "agentsflow": [{"id": 557874, "mc": 27, "oc": 5}], "aga": [{"id": 558160, "mc": 84, "oc": 9}], "agustu": [{"id": 559938, "mc": 3413, "oc": 74}], "agro": [{"id": 560050, "mc": 88, "oc": 15}, {"id": 722660, "mc": 3472, "oc": 665}, {"id": 726761, "mc": 39, "oc": 7}, {"id": 747261, "mc": 1310, "oc": 63}], "agentlv": [{"id": 562270, "mc": 7, "oc": 5}], "agertham": [{"id": 564697, "mc": 21, "oc": 5}], "agencygrow": [{"id": 565320, "mc": 687, "oc": 57}], "agentacademy": [{"id": 565667, "mc": 841, "oc": 187}], "agp": [{"id": 567547, "mc": 1, "oc": 0}, {"id": 745376, "mc": 68, "oc": 13}], "agustina": [{"id": 567657, "mc": 5, "oc": 0}], "agd": [{"id": 567715, "mc": 14, "oc": 10}], "agence": [{"id": 568356, "mc": 257, "oc": 34}, {"id": 619589, "mc": 12, "oc": 4}, {"id": 703738, "mc": 156, "oc": 17}], "agminum": [{"id": 568694, "mc": 175, "oc": 25}], "agenthq": [{"id": 573823, "mc": 172, "oc": 16}], "agtra": [{"id": 576778, "mc": 4, "oc": 1}], "agentstation": [{"id": 577232, "mc": 33, "oc": 6}], "aguacate": [{"id": 580739, "mc": 5, "oc": 4}, {"id": 661697, "mc": 97, "oc": 25}], "agile459": [{"id": 580790, "mc": 77, "oc": 18}], "aggregate": [{"id": 581156, "mc": 113, "oc": 25}], "agenzy": [{"id": 581867, "mc": 4, "oc": 2}], "agapetusyt": [{"id": 581934, "mc": 1, "oc": 0}], "agcorp": [{"id": 582632, "mc": 117, "oc": 11}], "agentscope": [{"id": 583133, "mc": 291, "oc": 20}], "ageofcard": [{"id": 584863, "mc": 51, "oc": 10}], "agusbob": [{"id": 586677, "mc": 21078, "oc": 1295}], "agocord": [{"id": 586903, "mc": 4, "oc": 0}], "agot": [{"id": 587425, "mc": 57, "oc": 3}], "agrwal": [{"id": 589585, "mc": 113, "oc": 4}], "agressgent": [{"id": 591348, "mc": 3382, "oc": 136}], "agibot": [{"id": 592241, "mc": 58, "oc": 6}], "agrigrow": [{"id": 592516, "mc": 161, "oc": 10}], "agony": [{"id": 593035, "mc": 33, "oc": 10}, {"id": 611000, "mc": 651, "oc": 97}, {"id": 644472, "mc": 72, "oc": 11}, {"id": 656830, "mc": 14, "oc": 9}, {"id": 711966, "mc": 262, "oc": 58}, {"id": 732284, "mc": 310, "oc": 17}], "agiota": [{"id": 593300, "mc": 5, "oc": 1}, {"id": 748340, "mc": 2, "oc": 0}], "aggienation": [{"id": 594049, "mc": 193, "oc": 20}], "agressivehummer": [{"id": 594835, "mc": 9, "oc": 6}], "agentaika": [{"id": 595726, "mc": 16, "oc": 2}], "agender": [{"id": 599305, "mc": 3, "oc": 1}, {"id": 644213, "mc": 154, "oc": 22}, {"id": 683450, "mc": 277, "oc": 52}, {"id": 726733, "mc": 282, "oc": 24}], "agranak": [{"id": 600062, "mc": 168, "oc": 23}], "agape": [{"id": 604585, "mc": 14, "oc": 3}], "agiriko": [{"id": 605366, "mc": 380, "oc": 101}], "agw": [{"id": 605533, "mc": 124, "oc": 13}], "agewa": [{"id": 606663, "mc": 1, "oc": 0}], "agarzrc": [{"id": 607330, "mc": 1100, "oc": 11}], "agincourt": [{"id": 607394, "mc": 262, "oc": 21}], "agrarplay": [{"id": 607699, "mc": 26391, "oc": 2193}], "agexp": [{"id": 608543, "mc": 88, "oc": 27}], "agentx": [{"id": 610596, "mc": 118, "oc": 11}], "agatha": [{"id": 612493, "mc": 30, "oc": 1}], "agronome": [{"id": 613994, "mc": 138, "oc": 4}], "agilebaltimore": [{"id": 616343, "mc": 67, "oc": 6}], "agriu": [{"id": 616355, "mc": 18, "oc": 4}], "agnb": [{"id": 617930, "mc": 7, "oc": 1}], "aggressive": [{"id": 619210, "mc": 4, "oc": 1}], "agario": [{"id": 619865, "mc": 6212, "oc": 242}], "aggrogahu": [{"id": 620919, "mc": 258, "oc": 42}], "ageoftriton": [{"id": 622756, "mc": 1, "oc": 0}], "agtl": [{"id": 623414, "mc": 27, "oc": 12}], "aguado": [{"id": 624319, "mc": 63, "oc": 9}], "agt": [{"id": 627459, "mc": 197, "oc": 20}], "agk": [{"id": 628026, "mc": 88, "oc": 10}], "agoner": [{"id": 629039, "mc": 44, "oc": 8}], "aganstomaki": [{"id": 629690, "mc": 19, "oc": 7}], "agamemnon": [{"id": 632252, "mc": 706, "oc": 79}], "agencia": [{"id": 633853, "mc": 21, "oc": 1}, {"id": 633951, "mc": 12, "oc": 3}, {"id": 740602, "mc": 87, "oc": 14}], "aguch02": [{"id": 636120, "mc": 123, "oc": 20}], "agopole": [{"id": 636391, "mc": 13, "oc": 2}], "agustaso": [{"id": 638002, "mc": 35, "oc": 11}], "agian": [{"id": 638209, "mc": 4, "oc": 0}], "agencyplayersmeet": [{"id": 642841, "mc": 184, "oc": 46}], "aguara": [{"id": 643370, "mc": 49, "oc": 7}], "agenor": [{"id": 643942, "mc": 14877, "oc": 29}], "agualimon": [{"id": 646915, "mc": 682, "oc": 70}], "agalarla": [{"id": 646916, "mc": 5, "oc": 0}], "ag94": [{"id": 647034, "mc": 102, "oc": 9}], "agencylab": [{"id": 651536, "mc": 39, "oc": 3}], "agen": [{"id": 652948, "mc": 64, "oc": 14}], "aglgamesdev": [{"id": 654060, "mc": 19, "oc": 5}], "agation": [{"id": 654165, "mc": 392, "oc": 132}], "agathor": [{"id": 656242, "mc": 17, "oc": 7}], "agiflow": [{"id": 658146, "mc": 9, "oc": 0}], "agm": [{"id": 659569, "mc": 84, "oc": 38}], "agnossiu": [{"id": 659828, "mc": 6, "oc": 4}], "agagtv": [{"id": 661510, "mc": 513, "oc": 19}], "agencie": [{"id": 663371, "mc": 258, "oc": 34}], "ageofz": [{"id": 663613, "mc": 44, "oc": 1}], "agnivision": [{"id": 665072, "mc": 128, "oc": 3}], "agreiver": [{"id": 666646, "mc": 22, "oc": 3}], "agenting": [{"id": 667533, "mc": 14, "oc": 7}], "agri": [{"id": 667546, "mc": 255, "oc": 87}], "aggroholic": [{"id": 668348, "mc": 148, "oc": 38}], "agarz": [{"id": 669982, "mc": 37387, "oc": 152}], "agarv": [{"id": 673315, "mc": 175, "oc": 21}], "agonia": [{"id": 673757, "mc": 1198, "oc": 212}], "ago": [{"id": 674168, "mc": 1076, "oc": 119}, {"id": 689284, "mc": 12, "oc": 5}], "agentwood": [{"id": 674274, "mc": 3806, "oc": 72}], "agentwigggle": [{"id": 676365, "mc": 8, "oc": 2}], "agrona": [{"id": 676660, "mc": 11, "oc": 6}], "agoniapg": [{"id": 677559, "mc": 168, "oc": 36}], "aguix": [{"id": 678068, "mc": 7, "oc": 3}], "agnori": [{"id": 678648, "mc": 87, "oc": 31}], "aggiecon": [{"id": 679364, "mc": 531, "oc": 115}], "agun": [{"id": 680822, "mc": 588, "oc": 115}], "agricola": [{"id": 683188, "mc": 190, "oc": 25}], "aghl": [{"id": 685921, "mc": 357, "oc": 44}], "agamotto": [{"id": 689039, "mc": 12, "oc": 3}], "agoodday": [{"id": 689735, "mc": 105, "oc": 21}], "agua": [{"id": 693344, "mc": 1657, "oc": 9}, {"id": 728612, "mc": 9, "oc": 4}], "agb": [{"id": 694278, "mc": 47, "oc": 2}], "agujero": [{"id": 694644, "mc": 12, "oc": 4}], "aging": [{"id": 695156, "mc": 704, "oc": 126}], "agedacc": [{"id": 695314, "mc": 6064, "oc": 869}], "agariocity": [{"id": 698973, "mc": 552, "oc": 31}], "agrio": [{"id": 700888, "mc": 177, "oc": 6}], "agreeland": [{"id": 703498, "mc": 274, "oc": 58}], "agregore": [{"id": 705821, "mc": 201, "oc": 24}], "agosto": [{"id": 707750, "mc": 985, "oc": 36}], "agalar": [{"id": 709050, "mc": 543, "oc": 20}], "agz": [{"id": 709281, "mc": 24, "oc": 6}], "agnostipay": [{"id": 709441, "mc": 2, "oc": 0}], "agarra": [{"id": 710658, "mc": 20, "oc": 3}], "agh": [{"id": 712680, "mc": 535, "oc": 1}], "agrarhorn": [{"id": 714127, "mc": 8, "oc": 0}], "aggronite": [{"id": 714475, "mc": 17, "oc": 3}], "agentwxo": [{"id": 714860, "mc": 76, "oc": 3}], "aggretscord": [{"id": 717144, "mc": 1834, "oc": 534}], "agentuniverse": [{"id": 719413, "mc": 49, "oc": 3}], "agoo": [{"id": 719818, "mc": 35, "oc": 6}], "agaropedia": [{"id": 723930, "mc": 15, "oc": 5}], "agbdogserver": [{"id": 726220, "mc": 2, "oc": 0}], "agrocultura": [{"id": 728129, "mc": 5, "oc": 1}], "agarpower": [{"id": 729384, "mc": 581, "oc": 23}], "agf": [{"id": 730161, "mc": 31, "oc": 3}], "agrocybernetyka": [{"id": 733351, "mc": 64, "oc": 1}], "agrassar": [{"id": 735492, "mc": 31, "oc": 0}], "aggiemation": [{"id": 738363, "mc": 345, "oc": 25}], "aghesy": [{"id": 738550, "mc": 32, "oc": 12}], "agenti": [{"id": 739118, "mc": 235, "oc": 81}], "agni": [{"id": 740398, "mc": 10, "oc": 2}], "agentfun": [{"id": 740670, "mc": 1781, "oc": 89}], "agelimc": [{"id": 741040, "mc": 12, "oc": 2}], "agoe": [{"id": 741538, "mc": 12, "oc": 9}], "aggenftw": [{"id": 742509, "mc": 228, "oc": 30}], "agli": [{"id": 743506, "mc": 9187, "oc": 1278}], "agravity": [{"id": 746210, "mc": 83, "oc": 19}], "agriut": [{"id": 746816, "mc": 237, "oc": 5}], "aguacero": [{"id": 748464, "mc": 261, "oc": 71}], "agresifdoktor": [{"id": 749269, "mc": 238, "oc": 10}]}