{"ii": [{"id": 509652, "mc": 1359, "oc": 124}, {"id": 513264, "mc": 2152, "oc": 227}, {"id": 518034, "mc": 741, "oc": 77}, {"id": 522004, "mc": 1105, "oc": 101}, {"id": 522219, "mc": 17427, "oc": 251}, {"id": 530455, "mc": 1010, "oc": 64}, {"id": 536025, "mc": 2124, "oc": 263}, {"id": 536025, "mc": 2124, "oc": 263}, {"id": 548261, "mc": 791, "oc": 27}, {"id": 554265, "mc": 30102, "oc": 7047}, {"id": 559638, "mc": 8530, "oc": 323}, {"id": 563187, "mc": 457, "oc": 75}, {"id": 569077, "mc": 846, "oc": 140}, {"id": 592158, "mc": 1667, "oc": 85}, {"id": 592736, "mc": 427, "oc": 39}, {"id": 604255, "mc": 236, "oc": 38}, {"id": 613646, "mc": 42, "oc": 16}, {"id": 613736, "mc": 474, "oc": 153}, {"id": 618236, "mc": 284, "oc": 34}, {"id": 629409, "mc": 118, "oc": 30}, {"id": 632182, "mc": 679, "oc": 360}, {"id": 632721, "mc": 126083, "oc": 24830}, {"id": 639161, "mc": 31, "oc": 13}, {"id": 640215, "mc": 341, "oc": 45}, {"id": 640568, "mc": 89, "oc": 23}, {"id": 641943, "mc": 13583, "oc": 1947}, {"id": 646870, "mc": 322, "oc": 72}, {"id": 672364, "mc": 122, "oc": 43}, {"id": 684779, "mc": 4633, "oc": 712}, {"id": 686302, "mc": 108, "oc": 6}, {"id": 687161, "mc": 5805, "oc": 1723}, {"id": 691675, "mc": 1626, "oc": 171}, {"id": 709227, "mc": 198, "oc": 26}, {"id": 733578, "mc": 22190, "oc": 3668}, {"id": 744492, "mc": 262, "oc": 58}], "iitai": [{"id": 518037, "mc": 193, "oc": 30}], "iii": [{"id": 526423, "mc": 15, "oc": 4}, {"id": 541209, "mc": 21322, "oc": 5657}, {"id": 541436, "mc": 531, "oc": 77}, {"id": 572069, "mc": 3202, "oc": 272}, {"id": 593178, "mc": 244, "oc": 21}, {"id": 598265, "mc": 363, "oc": 79}, {"id": 613512, "mc": 127, "oc": 16}, {"id": 627855, "mc": 682, "oc": 158}, {"id": 632843, "mc": 90, "oc": 14}, {"id": 683742, "mc": 8849, "oc": 3152}, {"id": 683912, "mc": 216, "oc": 38}, {"id": 715833, "mc": 33, "oc": 12}, {"id": 729646, "mc": 1799, "oc": 137}, {"id": 730162, "mc": 1249, "oc": 183}, {"id": 733160, "mc": 119, "oc": 47}], "iit": [{"id": 526543, "mc": 5610, "oc": 89}], "iikawarii": [{"id": 554355, "mc": 80, "oc": 23}], "iinstitutional": [{"id": 588771, "mc": 223, "oc": 21}], "iim": [{"id": 591106, "mc": 1619, "oc": 371}, {"id": 591106, "mc": 1619, "oc": 371}], "iiit": [{"id": 596332, "mc": 517, "oc": 9}], "iidk": [{"id": 611144, "mc": 125202, "oc": 18858}], "iidx": [{"id": 642045, "mc": 2398, "oc": 816}], "iis": [{"id": 681069, "mc": 23, "oc": 4}, {"id": 732743, "mc": 298, "oc": 36}]}