{"qdbe4mtpfq": [{"id": 501642, "mc": 5356, "oc": 860}], "qdns65pmck": [{"id": 502679, "mc": 561, "oc": 56}], "qdvkx8f": [{"id": 504479, "mc": 39, "oc": 9}], "qdqdp52kqr": [{"id": 506305, "mc": 216, "oc": 22}], "qdcswtamwx": [{"id": 506761, "mc": 4, "oc": 2}], "qdkfyma": [{"id": 507307, "mc": 41, "oc": 9}], "qde7q5j2db": [{"id": 508072, "mc": 291, "oc": 36}], "qdtq8t9zdj": [{"id": 509607, "mc": 58, "oc": 10}], "qdhcchqt2r": [{"id": 510530, "mc": 31, "oc": 6}], "qdjhyjfuqc": [{"id": 510710, "mc": 1250, "oc": 249}], "qdzqnw4axv": [{"id": 511142, "mc": 360, "oc": 22}], "qdrt4dkssb": [{"id": 514546, "mc": 95, "oc": 16}], "qddh9ga9u": [{"id": 518204, "mc": 66, "oc": 9}], "qdnxgynvgj": [{"id": 519378, "mc": 72, "oc": 19}], "qdrnbnh": [{"id": 520229, "mc": 12, "oc": 1}], "qdsb5fzpmr": [{"id": 520264, "mc": 475, "oc": 5}], "qdc4t7enet": [{"id": 522099, "mc": 10, "oc": 5}], "qdvnygp": [{"id": 523507, "mc": 43, "oc": 9}], "qdrpznexyk": [{"id": 524175, "mc": 253, "oc": 24}], "qddrphqrde": [{"id": 524509, "mc": 3461, "oc": 4}], "qdqjk6e": [{"id": 524625, "mc": 226, "oc": 29}], "qdrg98bhcc": [{"id": 527585, "mc": 292, "oc": 43}], "qdn9btm": [{"id": 529649, "mc": 110, "oc": 18}], "qdjdkkg": [{"id": 530850, "mc": 155, "oc": 21}], "qdkjzdwwhj": [{"id": 531076, "mc": 6261, "oc": 2775}], "qdnwkac6db": [{"id": 532325, "mc": 363, "oc": 20}], "qdsn3t6qj2": [{"id": 533077, "mc": 19, "oc": 3}], "qdwvzh9b5v": [{"id": 534292, "mc": 8, "oc": 0}], "qdvuunx": [{"id": 539291, "mc": 13, "oc": 0}], "qdgqtjt437": [{"id": 539514, "mc": 381, "oc": 9}], "qdmyrzn": [{"id": 540124, "mc": 51, "oc": 11}], "qdpvq4xagx": [{"id": 540199, "mc": 29, "oc": 14}], "qdghcvr7h": [{"id": 542370, "mc": 8, "oc": 1}], "qdzrjcxtqz": [{"id": 542627, "mc": 23, "oc": 9}], "qdxran5": [{"id": 543031, "mc": 2845, "oc": 242}], "qd2argepcx": [{"id": 543873, "mc": 364, "oc": 13}], "qdvdyfyrxp": [{"id": 546254, "mc": 201, "oc": 55}], "qd39uck": [{"id": 546400, "mc": 23, "oc": 3}], "qdtt6kcfyh": [{"id": 546695, "mc": 400, "oc": 15}], "qdz32qh": [{"id": 548298, "mc": 19, "oc": 3}], "qduefnf": [{"id": 549025, "mc": 1225, "oc": 46}], "qd8krx7ktk": [{"id": 549096, "mc": 209, "oc": 54}], "qdpdzsuypv": [{"id": 550748, "mc": 4, "oc": 1}], "qdz8g4d3mf": [{"id": 553961, "mc": 25, "oc": 7}], "qdkwpyqjdb": [{"id": 554772, "mc": 101, "oc": 21}], "qdpb4dcq4d": [{"id": 555275, "mc": 23, "oc": 6}], "qdtv5wbnqe": [{"id": 555860, "mc": 1, "oc": 0}], "qdtydqzh2e": [{"id": 557506, "mc": 106, "oc": 28}], "qdruaxj": [{"id": 558602, "mc": 7, "oc": 1}], "qdgt6d7azr": [{"id": 560449, "mc": 3, "oc": 0}], "qdg6mpzwam": [{"id": 561861, "mc": 219, "oc": 72}], "qdegvsvcr": [{"id": 562129, "mc": 68, "oc": 11}], "qdtp5uemn8": [{"id": 564475, "mc": 10892, "oc": 515}], "qdt9ycrkmv": [{"id": 564991, "mc": 27, "oc": 2}], "qd5ctxdgjh": [{"id": 565564, "mc": 32, "oc": 12}], "qdgugeyp6k": [{"id": 565718, "mc": 379, "oc": 197}], "qdcdexphpy": [{"id": 572936, "mc": 82, "oc": 22}], "qdu2hsengh": [{"id": 574064, "mc": 3023, "oc": 283}], "qd6yd9jdpg": [{"id": 574431, "mc": 2300, "oc": 166}], "qdc2wayvnb": [{"id": 576040, "mc": 264, "oc": 29}], "qdc4qru": [{"id": 579533, "mc": 38, "oc": 5}], "qdc6u32z5u": [{"id": 582015, "mc": 136, "oc": 23}], "qdh4rdzqcc": [{"id": 584901, "mc": 13624, "oc": 3565}], "qdemx3xrjc": [{"id": 585045, "mc": 518, "oc": 38}], "qddw9956te": [{"id": 587743, "mc": 2766, "oc": 82}], "qdc7e9n": [{"id": 590551, "mc": 123, "oc": 38}], "qd9xebzbxz": [{"id": 591447, "mc": 2936, "oc": 16}], "qdspwyyxd3": [{"id": 594308, "mc": 70, "oc": 23}], "qdut8hpcvr": [{"id": 595010, "mc": 13075, "oc": 2340}], "qdzspuk9ge": [{"id": 595336, "mc": 40, "oc": 7}], "qdwaghacmx": [{"id": 595706, "mc": 8, "oc": 5}], "qd92nkjdde": [{"id": 596856, "mc": 3230, "oc": 158}], "qdj6cdb": [{"id": 600211, "mc": 736, "oc": 41}], "qd3dzsvv8f": [{"id": 600317, "mc": 35, "oc": 8}], "qdsxjpfvvt": [{"id": 605006, "mc": 78, "oc": 13}], "qd69zhgu7t": [{"id": 605548, "mc": 27, "oc": 2}], "qdyrba": [{"id": 606286, "mc": 13, "oc": 0}], "qd7pqfn": [{"id": 608174, "mc": 213, "oc": 28}], "qdcmfv7": [{"id": 609321, "mc": 23, "oc": 4}], "qds49avqxh": [{"id": 609444, "mc": 43, "oc": 12}], "qd4yqbaen2": [{"id": 610507, "mc": 1602, "oc": 66}], "qdmsjxn6hn": [{"id": 612035, "mc": 134, "oc": 23}], "qdsj9ywtjt": [{"id": 616057, "mc": 9385, "oc": 2125}], "qd2nuse": [{"id": 619378, "mc": 6, "oc": 3}], "qdpqz7w7fj": [{"id": 620194, "mc": 54, "oc": 6}], "qdxjbpa": [{"id": 622924, "mc": 4004, "oc": 813}], "qdre89e": [{"id": 626964, "mc": 87, "oc": 10}], "qdcfet5tc7": [{"id": 628661, "mc": 474, "oc": 104}], "qdy4jvv": [{"id": 628863, "mc": 100, "oc": 13}], "qdwb5a5gnn": [{"id": 629901, "mc": 142, "oc": 39}], "qd3becwyuw": [{"id": 631114, "mc": 526, "oc": 30}], "qdrakya": [{"id": 631138, "mc": 212, "oc": 39}], "qdpgrxv": [{"id": 631361, "mc": 24, "oc": 2}], "qdp9jwxtey": [{"id": 632742, "mc": 34, "oc": 12}], "qdqqhj47hp": [{"id": 634722, "mc": 14, "oc": 7}], "qdevkhg": [{"id": 634916, "mc": 62, "oc": 14}], "qdur4ka": [{"id": 634948, "mc": 304, "oc": 19}], "qdbb26pr7j": [{"id": 639479, "mc": 118, "oc": 32}], "qdpvfvrzty": [{"id": 640076, "mc": 1, "oc": 0}], "qdpx8s7": [{"id": 640809, "mc": 67, "oc": 2}], "qdwmf5t4xa": [{"id": 640951, "mc": 320, "oc": 77}], "qdvjcytgux": [{"id": 642328, "mc": 80, "oc": 24}], "qdzds8wrtn": [{"id": 642367, "mc": 49, "oc": 14}], "qdeemnpj36": [{"id": 642879, "mc": 1, "oc": 0}], "qdqghwxvmn": [{"id": 644464, "mc": 4, "oc": 0}], "qdcssdyhpj": [{"id": 649059, "mc": 290, "oc": 22}], "qd2nwtv": [{"id": 649104, "mc": 78, "oc": 27}], "qdtys65c86": [{"id": 649272, "mc": 27, "oc": 9}], "qdmbv7hkb8": [{"id": 651095, "mc": 145, "oc": 15}], "qdehuscvkf": [{"id": 652336, "mc": 147, "oc": 84}], "qddb5w4": [{"id": 652994, "mc": 483, "oc": 49}], "qdmhyyjxwq": [{"id": 653343, "mc": 19, "oc": 1}], "qdtcg4e": [{"id": 662445, "mc": 275, "oc": 20}], "qdrhtga": [{"id": 663370, "mc": 17, "oc": 2}], "qdz7wgg": [{"id": 664551, "mc": 9, "oc": 3}], "qd7qzxkpje": [{"id": 666663, "mc": 54, "oc": 12}], "qdk9ryg7w2": [{"id": 669744, "mc": 20, "oc": 2}], "qdfvqbn3gy": [{"id": 670926, "mc": 71, "oc": 16}], "qdthgztrjy": [{"id": 672018, "mc": 7335, "oc": 1533}], "qdjagqf": [{"id": 672518, "mc": 49, "oc": 8}], "qd9rabf": [{"id": 677450, "mc": 104, "oc": 21}], "qd3puv7vgx": [{"id": 677687, "mc": 80, "oc": 28}], "qd2sqja": [{"id": 677976, "mc": 4, "oc": 0}], "qdshkxrr2c": [{"id": 678447, "mc": 18, "oc": 2}], "qdn9twkhhc": [{"id": 680233, "mc": 30, "oc": 12}], "qdnthg69nk": [{"id": 681673, "mc": 1159, "oc": 87}], "qd8xfjfmce": [{"id": 686459, "mc": 133, "oc": 31}], "qdcnfmc": [{"id": 690949, "mc": 127, "oc": 37}], "qdcyt7fesd": [{"id": 693702, "mc": 89, "oc": 30}], "qdrukhwtkn": [{"id": 694327, "mc": 58, "oc": 16}], "qdujhjqwcu": [{"id": 694516, "mc": 8, "oc": 0}], "qdcgp8mtfy": [{"id": 695172, "mc": 188, "oc": 81}], "qdwmahzdpm": [{"id": 695627, "mc": 520, "oc": 45}], "qdc9nagxjy": [{"id": 695848, "mc": 29, "oc": 5}], "qdv5zyzv3r": [{"id": 697231, "mc": 9, "oc": 0}], "qdsqsq9a6v": [{"id": 697847, "mc": 173, "oc": 22}], "qdezpy4qtv": [{"id": 699147, "mc": 69358, "oc": 3083}], "qdzn5qtw8": [{"id": 699307, "mc": 59, "oc": 9}], "qd6pngxhwf": [{"id": 699978, "mc": 85, "oc": 1}], "qdvf4gpyup": [{"id": 701127, "mc": 141, "oc": 15}], "qdbcfphhuk": [{"id": 702506, "mc": 66, "oc": 3}], "qdnm7euxwz": [{"id": 703516, "mc": 64, "oc": 22}], "qdewgxv": [{"id": 703784, "mc": 75, "oc": 14}], "qd4h5bb": [{"id": 704107, "mc": 83, "oc": 12}], "qdn9s2wan": [{"id": 705861, "mc": 201, "oc": 83}], "qd74am4hzc": [{"id": 707273, "mc": 36, "oc": 16}], "qdjqj3y": [{"id": 707435, "mc": 29, "oc": 7}], "qdmy22brxw": [{"id": 710565, "mc": 90, "oc": 22}], "qdmjxgv4am": [{"id": 713952, "mc": 2165, "oc": 843}], "qdqhzug": [{"id": 713956, "mc": 89, "oc": 13}], "qdwaesnpbc": [{"id": 715211, "mc": 37, "oc": 15}], "qdarvvm": [{"id": 719169, "mc": 383, "oc": 15}], "qd9sncwmzt": [{"id": 725348, "mc": 520, "oc": 24}], "qdc6juv": [{"id": 727750, "mc": 741, "oc": 115}], "qdpqprn": [{"id": 727956, "mc": 83, "oc": 10}], "qdtcqedpu9": [{"id": 728351, "mc": 180, "oc": 10}], "qdrywzt8nq": [{"id": 729630, "mc": 140, "oc": 3}], "qdmjqt6f7t": [{"id": 732195, "mc": 16, "oc": 8}], "qdr74ub": [{"id": 732379, "mc": 1618, "oc": 30}], "qd9wkzppxy": [{"id": 732734, "mc": 53, "oc": 6}], "qde3z6mf2b": [{"id": 736898, "mc": 49, "oc": 9}], "qd3gqv": [{"id": 738429, "mc": 35, "oc": 14}], "qd7m3v6edx": [{"id": 738621, "mc": 250, "oc": 74}], "qdrw9zt": [{"id": 744022, "mc": 14, "oc": 9}], "qddh6y2": [{"id": 746828, "mc": 338, "oc": 22}], "qddzjmfyx": [{"id": 748768, "mc": 37, "oc": 10}]}